google_sheet_writer/__init__.py
google_sheet_writer/classes.py
google_sheet_writer/version.py
google_sheet_writer-0.0.7.dist-info/LICENSE.md
google_sheet_writer-0.0.7.dist-info/METADATA
google_sheet_writer-0.0.7.dist-info/WHEEL
google_sheet_writer-0.0.7.dist-info/top_level.txt
google_sheet_writer-0.0.7.dist-info/RECORD
