Metadata-Version: 2.2
Name: google_sheet_writer
Version: 0.0.7
Summary: Easy wrapper around gspread and gspread-formatting
Home-page: https://gitlab.com/peczony/google_sheet_writer
Author: Alexander Pecheny
Author-email: ap@pecheny.me
Classifier: Programming Language :: Python :: 3
Classifier: License :: OSI Approved :: MIT License
Classifier: Operating System :: OS Independent
License-File: LICENSE.md
Requires-Dist: gspread
Requires-Dist: gspread-formatting
Dynamic: author
Dynamic: author-email
Dynamic: classifier
Dynamic: description
Dynamic: description-content-type
Dynamic: home-page
Dynamic: requires-dist
Dynamic: summary
